qbroker
