Metadata-Version: 1.1
Name: QBroker
Version: 0.30.8
Summary: QBroker is a minimal async wrapper for RPC via AMQP
Home-page: https://github.com/M-o-a-T/qbroker
Author: Matthias Urlichs
Author-email: matthias@urlichs.de
License: GPLv3+
Platform: UNKNOWN
Classifier: Development Status :: 4 - Beta
Classifier: Intended Audience :: Developers
Classifier: License :: OSI Approved :: GNU General Public License v3 or later (GPLv3+)
Classifier: Natural Language :: English
Classifier: Operating System :: OS Independent
Classifier: Programming Language :: Python
Classifier: Topic :: Software Development :: Libraries :: Application Frameworks
Classifier: Topic :: Software Development :: Libraries :: Python Modules
Classifier: Topic :: Utilities
